setup.py
distributionsvicky/Binomialdistribution.py
distributionsvicky/Gaussiandistribution.py
distributionsvicky/Generaldistribution.py
distributionsvicky/__init__.py
distributionsvicky.egg-info/PKG-INFO
distributionsvicky.egg-info/SOURCES.txt
distributionsvicky.egg-info/dependency_links.txt
distributionsvicky.egg-info/not-zip-safe
distributionsvicky.egg-info/top_level.txt